{
  "resource": "Countries",
  "resource_explanation": null,
  "http_method": "GET",
  "route": "/countries",
  "description": "List countries",
  "explanation": null,
  "parameters": [

  ],
  "response_fields": [

  ],
  "requests": [
    {
      "request_method": "GET",
      "request_path": "/countries",
      "request_body": null,
      "request_headers": {
        "Host": "example.org",
        "Cookie": ""
      },
      "request_query_parameters": {
      },
      "request_content_type": null,
      "response_status": 200,
      "response_status_text": "OK",
      "response_body": "{\n  \"countries\": [\n    {\n      \"id\": \"5cf586c153a63446b0146462\",\n      \"name\": \"Belgium\"\n    },\n    {\n      \"id\": \"5cf586c153a63446b0146463\",\n      \"name\": \"Slovenia\"\n    },\n    {\n      \"id\": \"5cf586c153a63446b0146464\",\n      \"name\": \"Azerbaijan\"\n    },\n    {\n      \"id\": \"5cf586c153a63446b0146465\",\n      \"name\": \"Botswana\"\n    },\n    {\n      \"id\": \"5cf586c153a63446b0146466\",\n      \"name\": \"Puerto Rico\"\n    },\n    {\n      \"id\": \"5cf586c153a63446b0146467\",\n      \"name\": \"Montserrat\"\n    },\n    {\n      \"id\": \"5cf586c153a63446b0146468\",\n      \"name\": \"Paraguay\"\n    },\n    {\n      \"id\": \"5cf586c153a63446b0146469\",\n      \"name\": \"Somalia\"\n    },\n    {\n      \"id\": \"5cf586c153a63446b014646a\",\n      \"name\": \"French Guiana\"\n    },\n    {\n      \"id\": \"5cf586c153a63446b014646b\",\n      \"name\": \"Serbia\"\n    }\n  ],\n  \"meta\": {\n    \"current_page\": 1,\n    \"next_page\": null,\n    \"prev_page\": null,\n    \"total_pages\": 1,\n    \"total_count\": 10,\n    \"page_size\": 25\n  }\n}",
      "response_headers": {
        "Content-Type": "application/json; charset=utf-8",
        "ETag": "W/\"263956e4cda1ed397d64a7921f4fc4fb\"",
        "Cache-Control": "max-age=0, private, must-revalidate",
        "X-Request-Id": "8fc61377-437e-486e-a15a-53b2952bd00e",
        "X-Runtime": "0.005766",
        "Content-Length": "651"
      },
      "response_content_type": "application/json; charset=utf-8",
      "curl": "curl -g \"http://localhost:3000/countries\" -X GET \\\n\t-H \"Host: example.org\" \\\n\t-H \"Cookie: \""
    }
  ]
}